partis_view-0.1.4.data/purelib/partis/view/__init__.py
partis_view-0.1.4.data/purelib/partis/view/manager.py
partis_view-0.1.4.data/purelib/partis/view/main_window.py
partis_view-0.1.4.data/purelib/partis/view/schema/__init__.py
partis_view-0.1.4.data/purelib/partis/view/schema/evaluated_w.py
partis_view-0.1.4.data/purelib/partis/view/schema/int_w.py
partis_view-0.1.4.data/purelib/partis/view/schema/union_w.py
partis_view-0.1.4.data/purelib/partis/view/schema/tree_edit_node.py
partis_view-0.1.4.data/purelib/partis/view/schema/optional_w.py
partis_view-0.1.4.data/purelib/partis/view/schema/pass_w.py
partis_view-0.1.4.data/purelib/partis/view/schema/tree_edit_w.py
partis_view-0.1.4.data/purelib/partis/view/schema/tree_edit_deligate.py
partis_view-0.1.4.data/purelib/partis/view/schema/hint_w.py
partis_view-0.1.4.data/purelib/partis/view/schema/name_w.py
partis_view-0.1.4.data/purelib/partis/view/schema/tree_node_map.py
partis_view-0.1.4.data/purelib/partis/view/schema/str_w.py
partis_view-0.1.4.data/purelib/partis/view/schema/color_w.py
partis_view-0.1.4.data/purelib/partis/view/schema/bool_w.py
partis_view-0.1.4.data/purelib/partis/view/schema/map_w.py
partis_view-0.1.4.data/purelib/partis/view/schema/list_w.py
partis_view-0.1.4.data/purelib/partis/view/schema/edit_w.py
partis_view-0.1.4.data/purelib/partis/view/schema/struct_w.py
partis_view-0.1.4.data/purelib/partis/view/schema/type_combo_w.py
partis_view-0.1.4.data/purelib/partis/view/schema/float_w.py
partis_view-0.1.4.data/purelib/partis/view/dialog/progress.py
partis_view-0.1.4.data/purelib/partis/view/dialog/__init__.py
partis_view-0.1.4.data/purelib/partis/view/dialog/log.py
partis_view-0.1.4.data/purelib/partis/view/dialog/hint.py
partis_view-0.1.4.data/purelib/partis/view/base/__init__.py
partis_view-0.1.4.data/purelib/partis/view/base/base.py
partis_view-0.1.4.data/purelib/partis/view/base/widget_stack.py
partis_view-0.1.4.data/purelib/partis/view/base/crumbs.py
partis_view-0.1.4.dist-info/METADATA
partis_view-0.1.4.dist-info/LICENSE.txt
partis_view-0.1.4.dist-info/top_level.txt
partis_view-0.1.4.dist-info/entry_points.txt
partis_view-0.1.4.dist-info/WHEEL
partis_view-0.1.4.dist-info/RECORD
