Metadata-Version: 2.1
Name: partis-view
Version: 0.1.4
Requires-Python: >=3.6.2
Maintainer-email: "Nanohmics Inc." <software.support@nanohmics.com>
Summary: Graphical interface for viewing and editing workflow files
License-File: LICENSE.txt
Classifier: Topic :: System :: Clustering
Classifier: Programming Language :: Python
Classifier: Intended Audience :: Science/Research
Classifier: Operating System :: POSIX :: Linux
Classifier: Development Status :: 4 - Beta
Classifier: License :: OSI Approved :: BSD License
Classifier: Programming Language :: Python :: 3
Classifier: Topic :: Scientific/Engineering
Provides-Extra: doc
Requires-Dist: Jinja2>=3.0.0
Requires-Dist: partis-utils[asy,theme]>=0.1.4
Requires-Dist: PySide2<5.15,>=5.14; python_version < "3.8"
Requires-Dist: PySide2<5.16,>=5.15; python_version >= "3.8"
Requires-Dist: scipy>=1.3.1
Requires-Dist: partis-schema>=0.1.4
Requires-Dist: partis-utils[sphinx]>=0.1.4; extra == "doc"
